caesar_cipher/__init__.py
caesar_cipher/analyzer.py
caesar_cipher/cipher.py
caesar_cipher/constants.py
caesar_cipher/main.py
caesar_cipher/utils.py
caesar_salad_cipher-0.1.0.dist-info/METADATA
caesar_salad_cipher-0.1.0.dist-info/WHEEL
caesar_salad_cipher-0.1.0.dist-info/entry_points.txt
caesar_salad_cipher-0.1.0.dist-info/RECORD
