Metadata-Version: 2.4
Name: caesar-salad-cipher
Version: 0.1.0
Summary: CLI tool that shifts characters by a specified number (the key) to encrypt/decrypt text.
Project-URL: Homepage, https://github.com/CarterPerez-dev/Cybersecurity-Projects/tree/main
Project-URL: Repository, https://github.com/CarterPerez-dev/Cybersecurity-Projects/tree/main/PROJECTS/caesar-cipher
Project-URL: Issues, https://github.com/CarterPerez-dev/Cybersecurity-Projects/tree/main/PROJECTS/caesar-cipher/issues
Requires-Python: >=3.12
Requires-Dist: rich<15.0.0,>=14.2.0
Requires-Dist: typer<0.21.0,>=0.20.0
Provides-Extra: dev
Requires-Dist: mypy<2.0.0,>=1.19.0; extra == 'dev'
Requires-Dist: pre-commit<5.0.0,>=4.5.0; extra == 'dev'
Requires-Dist: pylint<5.0.0,>=4.0.4; extra == 'dev'
Requires-Dist: pytest-cov<8.0.0,>=7.0.0; extra == 'dev'
Requires-Dist: pytest<10.0.0,>=9.0.2; extra == 'dev'
Requires-Dist: ruff<0.15.0,>=0.14.8; extra == 'dev'
Requires-Dist: ty<0.1.0,>=0.0.1a32; extra == 'dev'
